adapters/__init__.py
adapters/claude/__init__.py
adapters/claude/adapter.py
adapters/claude/handlers/__init__.py
adapters/claude/handlers/agent_handler.py
adapters/claude/handlers/perm_handler.py
adapters/claude/handlers/slash_command_handler.py
adapters/copilot/__init__.py
adapters/copilot/adapter.py
adapters/copilot/handlers/__init__.py
adapters/copilot/handlers/agent_handler.py
adapters/copilot/handlers/perm_handler.py
adapters/copilot/handlers/slash_command_handler.py
adapters/example/__init__.py
adapters/example/adapter.py
adapters/example/handlers/__init__.py
adapters/example/handlers/agent_handler.py
adapters/shared/__init__.py
adapters/shared/config_type_handler.py
adapters/shared/frontmatter.py
adapters/shared/utils.py
agent_sync-1.1.0.dist-info/licenses/LICENSE
cli/__init__.py
cli/main.py
core/__init__.py
core/_version.py
core/adapter_interface.py
core/canonical_models.py
core/orchestrator.py
core/registry.py
core/state_manager.py
scripts/__init__.py
scripts/build_executable.sh
scripts/sync_docs.py
agent_sync-1.1.0.dist-info/METADATA
agent_sync-1.1.0.dist-info/WHEEL
agent_sync-1.1.0.dist-info/entry_points.txt
agent_sync-1.1.0.dist-info/top_level.txt
agent_sync-1.1.0.dist-info/RECORD
