Metadata-Version: 2.4
Name: agent-sync
Version: 1.1.0
Summary: Bidirectional synchronization tool for custom agents and settings between Claude Code and GitHub Copilot.
Author-email: Zachery Glass <ZacheryGlass@users.noreply.github.com>
License: MIT
Classifier: Programming Language :: Python :: 3
Classifier: License :: OSI Approved :: MIT License
Classifier: Operating System :: OS Independent
Requires-Python: >=3.12
License-File: LICENSE
Requires-Dist: pyyaml>=6.0
Requires-Dist: requests>=2.28.0
Requires-Dist: beautifulsoup4>=4.11.0
Requires-Dist: html2text>=2020.1.16
Provides-Extra: dev
Requires-Dist: pytest>=7.0; extra == "dev"
Requires-Dist: requests-mock>=1.11.0; extra == "dev"
Requires-Dist: flake8; extra == "dev"
Requires-Dist: build; extra == "dev"
Requires-Dist: twine; extra == "dev"
Dynamic: license-file
